screenlly/__init__.py
screenlly/models.py
screenlly/utils.py
screenlly-0.0.12.dist-info/METADATA
screenlly-0.0.12.dist-info/WHEEL
screenlly-0.0.12.dist-info/top_level.txt
screenlly-0.0.12.dist-info/RECORD
