Metadata-Version: 2.1
Name: screenlly
Version: 0.0.12
Summary: Get and compare screenshots tool based on Selenium and ImageMagick
Author: Polina Mishchenko
Author-email: pefremova@gmail.com
Keywords: selenium,testing,test tool,screenshot,compare screenshots,full page screenshot
Classifier: Programming Language :: Python :: 3
Requires-Dist: selenium >=3.12.0
Requires-Dist: Pillow >=5.1.0
